ai/__init__.py
ai/zipline/__init__.py
ai/zipline/group_by.py
ai/zipline/join.py
ai/zipline/logger.py
ai/zipline/query.py
ai/zipline/utils.py
ai/zipline/api/__init__.py
ai/zipline/api/constants.py
ai/zipline/api/ttypes.py
ai/zipline/repo/__init__.py
ai/zipline/repo/compile.py
ai/zipline/repo/explore.py
ai/zipline/repo/extract_objects.py
ai/zipline/repo/run.py
ai/zipline/repo/serializer.py
ai/zipline/repo/teams.py
ai/zipline/repo/validator.py
chron-0.0.40.data/scripts/compile.py
chron-0.0.40.data/scripts/explore.py
chron-0.0.40.data/scripts/run.py
chron-0.0.40.dist-info/LICENSE
chron-0.0.40.dist-info/METADATA
chron-0.0.40.dist-info/WHEEL
chron-0.0.40.dist-info/top_level.txt
chron-0.0.40.dist-info/RECORD
