Metadata-Version: 2.1
Name: chron
Version: 0.0.40
Summary: Chron python API library
Home-page: UNKNOWN
License: UNKNOWN
Platform: UNKNOWN
Classifier: Programming Language :: Python :: 3.7
Requires-Python: >=3.7
License-File: LICENSE
Requires-Dist: click (==7.1.2)
Requires-Dist: thrift (==0.13.0)
